symphony_list/__init__.py
symphony_list/_frontend.py
symphony_list/_version.py
symphony_list/widget.py
symphony_list/labextension/build_log.json
symphony_list/labextension/package.json
symphony_list/labextension/static/lib_index_js.67f26e65b805a583abb6.js
symphony_list/labextension/static/lib_index_js.67f26e65b805a583abb6.js.map
symphony_list/labextension/static/lib_index_js.8e295ef9e7c0aed2b446.js
symphony_list/labextension/static/lib_index_js.8e295ef9e7c0aed2b446.js.map
symphony_list/labextension/static/remoteEntry.5b0bde40f9d48f26fefa.js
symphony_list/labextension/static/remoteEntry.5b0bde40f9d48f26fefa.js.map
symphony_list/labextension/static/remoteEntry.835c245fa5de327aafae.js
symphony_list/labextension/static/remoteEntry.835c245fa5de327aafae.js.map
symphony_list/labextension/static/style.js
symphony_list/nbextension/extension.js
symphony_list/nbextension/index.js
symphony_list/standalone/widgets/SymphonyList.js
symphony_list/standalone/widgets/SymphonyList.js.map
symphony_list-1.0.2.data/data/etc/jupyter/nbconfig/notebook.d/symphony_list.json
symphony_list-1.0.2.data/data/share/jupyter/labextensions/symphony-list/build_log.json
symphony_list-1.0.2.data/data/share/jupyter/labextensions/symphony-list/install.json
symphony_list-1.0.2.data/data/share/jupyter/labextensions/symphony-list/package.json
symphony_list-1.0.2.data/data/share/jupyter/labextensions/symphony-list/static/lib_index_js.8e295ef9e7c0aed2b446.js
symphony_list-1.0.2.data/data/share/jupyter/labextensions/symphony-list/static/lib_index_js.8e295ef9e7c0aed2b446.js.map
symphony_list-1.0.2.data/data/share/jupyter/labextensions/symphony-list/static/remoteEntry.835c245fa5de327aafae.js
symphony_list-1.0.2.data/data/share/jupyter/labextensions/symphony-list/static/remoteEntry.835c245fa5de327aafae.js.map
symphony_list-1.0.2.data/data/share/jupyter/labextensions/symphony-list/static/style.js
symphony_list-1.0.2.data/data/share/jupyter/nbextensions/symphony_list/extension.js
symphony_list-1.0.2.dist-info/LICENSE.txt
symphony_list-1.0.2.dist-info/METADATA
symphony_list-1.0.2.dist-info/WHEEL
symphony_list-1.0.2.dist-info/top_level.txt
symphony_list-1.0.2.dist-info/RECORD
